setup.py
duxlib/__init__.py
duxlib/_version.py
duxlib/bottle.py
duxlib/build.py
duxlib/collections.py
duxlib/copy.py
duxlib/funcy.py
duxlib/gzip.py
duxlib/json.py
duxlib/log.py
duxlib/mirror.py
duxlib/multimethod.py
duxlib/munkres.py
duxlib/numpy.py
duxlib/pandas.py
duxlib.egg-info/PKG-INFO
duxlib.egg-info/SOURCES.txt
duxlib.egg-info/dependency_links.txt
duxlib.egg-info/top_level.txt