Metadata-Version: 1.1
Name: duxlib
Version: 0.1.15
Summary: Extensions to Python libraries
Home-page: http://github.com/duckworthd/duxlib
Author: Daniel Duckworth
Author-email: duckworthd@gmail.com
License: BSD
Keywords: libraries extensions
Platform: UNKNOWN
Classifier: Development Status :: 4 - Beta
Classifier: License :: OSI Approved :: BSD License
Classifier: Operating System :: OS Independent
Classifier: Programming Language :: Python
